sdkrouter_tools/__init__.py
sdkrouter_tools/logging.py
sdkrouter_tools/html/__init__.py
sdkrouter_tools/html/cleaner/__init__.py
sdkrouter_tools/html/cleaner/aggressive.py
sdkrouter_tools/html/cleaner/cleaner.py
sdkrouter_tools/html/cleaner/config.py
sdkrouter_tools/html/cleaner/core.py
sdkrouter_tools/html/cleaner/focused.py
sdkrouter_tools/html/cleaner/models.py
sdkrouter_tools/html/cleaner/pipeline.py
sdkrouter_tools/html/cleaner/scripts.py
sdkrouter_tools/html/cleaner/classifiers/__init__.py
sdkrouter_tools/html/cleaner/classifiers/patterns.py
sdkrouter_tools/html/cleaner/classifiers/scorer.py
sdkrouter_tools/html/cleaner/extractors/__init__.py
sdkrouter_tools/html/cleaner/extractors/context.py
sdkrouter_tools/html/cleaner/extractors/hydration.py
sdkrouter_tools/html/cleaner/outputs/__init__.py
sdkrouter_tools/html/cleaner/outputs/aom_yaml.py
sdkrouter_tools/html/cleaner/outputs/markdown.py
sdkrouter_tools/html/cleaner/outputs/xtree.py
sdkrouter_tools/html/cleaner/transformers/__init__.py
sdkrouter_tools/html/cleaner/transformers/chunker.py
sdkrouter_tools/html/cleaner/transformers/downsampler.py
sdkrouter_tools/html/cleaner/transformers/shadow_dom.py
sdkrouter_tools/html/helpers/__init__.py
sdkrouter_tools/html/helpers/formatting.py
sdkrouter_tools/html/helpers/html.py
sdkrouter_tools/html/helpers/json_cleaner.py
sdkrouter_tools/telegram/__init__.py
sdkrouter_tools/telegram/exceptions.py
sdkrouter_tools/telegram/formatters.py
sdkrouter_tools/telegram/queue.py
sdkrouter_tools/telegram/sender.py
sdkrouter_tools/telegram/shortcuts.py
sdkrouter_tools/telegram/types.py
sdkrouter_tools/telegram/utils.py
sdkrouter_tools-0.1.2.dist-info/METADATA
sdkrouter_tools-0.1.2.dist-info/WHEEL
sdkrouter_tools-0.1.2.dist-info/RECORD
