Metadata-Version: 2.4
Name: sdkrouter-tools
Version: 0.1.2
Summary: SDK Router Tools — collection of utility tools for automation pipelines (telegram, logging, html cleaner, etc.)
Project-URL: Homepage, https://sdkrouter.com
Author-email: markolofsen <dev@markolofsen.com>
License-Expression: MIT
Keywords: automation,beautifulsoup,cleaner,html,llm,logging,markdown,notifications,queue,rich,scraping,telegram,tools
Classifier: Development Status :: 4 - Beta
Classifier: Intended Audience :: Developers
Classifier: License :: OSI Approved :: MIT License
Classifier: Programming Language :: Python :: 3
Classifier: Programming Language :: Python :: 3.10
Classifier: Programming Language :: Python :: 3.11
Classifier: Programming Language :: Python :: 3.12
Classifier: Topic :: Communications :: Chat
Classifier: Topic :: Software Development :: Libraries :: Python Modules
Requires-Python: >=3.10
Requires-Dist: beautifulsoup4>=4.12.0
Requires-Dist: lxml>=5.3.0
Requires-Dist: markdownify>=0.14.0
Requires-Dist: pydantic<3.0.0,>=2.10.0
Requires-Dist: pytelegrambotapi>=4.14.0
Requires-Dist: pyyaml>=6.0
Requires-Dist: rich>=13.0.0
Requires-Dist: tiktoken>=0.8.0
Requires-Dist: toon-python>=0.1.2
Provides-Extra: dev
Requires-Dist: build>=1.2.0; extra == 'dev'
Requires-Dist: mypy>=1.15.0; extra == 'dev'
Requires-Dist: pytest-cov>=6.0.0; extra == 'dev'
Requires-Dist: pytest>=8.3.0; extra == 'dev'
Requires-Dist: ruff>=0.9.0; extra == 'dev'
Requires-Dist: twine>=6.0.0; extra == 'dev'
